crawlster/__init__.py
crawlster/config.py
crawlster/core.py
crawlster/exceptions.py
crawlster/validators.py
crawlster/config/__init__.py
crawlster/config/config.py
crawlster/config/options.py
crawlster/handlers/__init__.py
crawlster/handlers/base.py
crawlster/handlers/jsonl.py
crawlster/handlers/log_handler.py
crawlster/handlers/stream.py
crawlster/handlers/db/__init__.py
crawlster/handlers/db/mongo.py
crawlster/helpers/__init__.py
crawlster/helpers/base.py
crawlster/helpers/extract.py
crawlster/helpers/log.py
crawlster/helpers/queue.py
crawlster/helpers/regex.py
crawlster/helpers/stats.py
crawlster/helpers/urls.py
crawlster/helpers/http/__init__.py
crawlster/helpers/http/request.py
crawlster/helpers/http/requests.py
crawlster/helpers/http/response.py
crawlster-0.1.1.dist-info/DESCRIPTION.rst
crawlster-0.1.1.dist-info/METADATA
crawlster-0.1.1.dist-info/RECORD
crawlster-0.1.1.dist-info/WHEEL
crawlster-0.1.1.dist-info/metadata.json
crawlster-0.1.1.dist-info/top_level.txt
examples/__init__.py
examples/first_look.py
examples/python_org.py
tests/__init__.py
tests/test_config.py
tests/test_crawlster.py
tests/helpers/__init__.py
tests/helpers/test_extract.py
tests/helpers/requests/__init__.py
tests/helpers/requests/test_http_request.py
tests/helpers/requests/test_http_response.py
