Metadata-Version: 2.0
Name: crawlster
Version: 0.1.1
Summary: None
Home-page: UNKNOWN
Author: UNKNOWN
Author-email: UNKNOWN
License: MIT
Platform: UNKNOWN
Classifier: Development Status :: 3 - Alpha
Classifier: Intended Audience :: Developers
Classifier: License :: OSI Approved :: MIT License
Classifier: Programming Language :: Python :: 3.5
Classifier: Programming Language :: Python :: 3.6
Classifier: Programming Language :: Python :: 3.7
Requires-Dist: colorlog
Requires-Dist: beautifulsoup4
Requires-Dist: requests
Provides-Extra: advanced
Requires-Dist: lxml; extra == 'advanced'
